AWS_MFA_Helper-1.1.0.dist-info/METADATA
AWS_MFA_Helper-1.1.0.dist-info/RECORD
AWS_MFA_Helper-1.1.0.dist-info/WHEEL
AWS_MFA_Helper-1.1.0.dist-info/entry_points.txt
AWS_MFA_Helper-1.1.0.dist-info/top_level.txt
aws_mfa_helper/__init__.py
aws_mfa_helper/cli.py
