Metadata-Version: 2.1
Name: AWS-MFA-Helper
Version: 1.1.0
Summary: Utility that obtains STS credentials and saves your AWS credentials file.
Home-page: https://github.com/jjfalling/AWS-MFA-Helper
Author: Jeremy Falling
License: GPLv3
Platform: UNKNOWN
Classifier: License :: OSI Approved :: GNU General Public License v3 (GPLv3)
Classifier: Programming Language :: Python
Classifier: Programming Language :: Python :: 2
Classifier: Programming Language :: Python :: 3
Classifier: Development Status :: 4 - Beta
Classifier: Intended Audience :: End Users/Desktop
Requires-Dist: boto (<3.0.0,>=2.48.0)
Requires-Dist: configparser (<4.0.0,>=3.5.0)
